hydrogen_pfhx/__init__.py
hydrogen_pfhx/bvp_model.py
hydrogen_pfhx/catalysts.py
hydrogen_pfhx/fluids.py
hydrogen_pfhx/heat_transfer_models.py
hydrogen_pfhx/helium_neon.py
hydrogen_pfhx/hexs.py
hydrogen_pfhx/hydrogen_thermodynamics.py
hydrogen_pfhx/model.py
hydrogen_pfhx/ortho_para_dynamics.py
hydrogen_pfhx/outputs.py
hydrogen_pfhx/pressure_models.py
hydrogen_pfhx/utils.py
hydrogen_pfhx-0.1.10.dist-info/LICENSE
hydrogen_pfhx-0.1.10.dist-info/METADATA
hydrogen_pfhx-0.1.10.dist-info/WHEEL
hydrogen_pfhx-0.1.10.dist-info/top_level.txt
hydrogen_pfhx-0.1.10.dist-info/RECORD
