Metadata-Version: 2.1
Name: hydrogen-pfhx
Version: 0.1.10
Summary: Chemical engineering model of hydrogen plate-fin heat exchanger
Author-email: Keelan O'Neill <keelan.oneill@uwa.edu.au>
License: BSD 3-Clause License
Project-URL: Homepage, https://github.com/fsr-uwa/hydrogen-pfhx
Keywords: hydrogen,pfhx,heat exchanger,ortho,para,engineering
Classifier: Programming Language :: Python :: 3
Classifier: License :: OSI Approved :: BSD License
Requires-Python: >=3.7
License-File: LICENSE
Requires-Dist: CoolProp >=6.4.1
Requires-Dist: matplotlib >=3.2.2
Requires-Dist: numpy >=1.21.6
Requires-Dist: pandas >=1.3.5
Requires-Dist: pyyaml >=6.0
Requires-Dist: scipy >=1.7.3
